[
null,
{"id":1,"expanded":false,"name":"mountain1","order":2,"parentId":0,"scrollX":1081.3333333333333,"scrollY":972.6666666666666},
{"id":2,"expanded":false,"name":"main","order":1,"parentId":0,"scrollX":1092,"scrollY":611.3333333333334},
{"id":3,"expanded":false,"name":"mountain2","order":3,"parentId":0,"scrollX":1081.3333333333333,"scrollY":972.6666666666666},
{"id":4,"expanded":false,"name":"MAP004","order":8,"parentId":0,"scrollX":1092,"scrollY":611.3333333333334},
{"id":5,"expanded":true,"name":"forest","order":4,"parentId":0,"scrollX":1232,"scrollY":1847.3333333333333},
{"id":6,"expanded":false,"name":"hell","order":5,"parentId":0,"scrollX":1092,"scrollY":611.3333333333334},
{"id":7,"expanded":false,"name":"purgatory","order":6,"parentId":0,"scrollX":1092,"scrollY":610.6666666666666},
null,
{"id":9,"expanded":false,"name":"cave","order":7,"parentId":0,"scrollX":1092,"scrollY":611.3333333333334}
]